vnc2flv_rec/__init__.py
vnc2flv_rec/lib/flvrec
vnc2flv_rec-0.2.0.dist-info/LICENSE
vnc2flv_rec-0.2.0.dist-info/METADATA
vnc2flv_rec-0.2.0.dist-info/WHEEL
vnc2flv_rec-0.2.0.dist-info/entry_points.txt
vnc2flv_rec-0.2.0.dist-info/top_level.txt
vnc2flv_rec-0.2.0.dist-info/RECORD
