Metadata-Version: 2.1
Name: vnc2flv-rec
Version: 0.2.0
Summary: Python3 wrapper for flvrec.py tool of vnc2flv
Home-page: https://github.com/imanazari70/vnc2flv-rec
Author: Iman Azari
Author-email: azari@mahsan.co
License: UNKNOWN
Platform: UNKNOWN
